README.md
setup.py
relex/__init__.py
relex.egg-info/PKG-INFO
relex.egg-info/SOURCES.txt
relex.egg-info/dependency_links.txt
relex.egg-info/requires.txt
relex.egg-info/top_level.txt
relex/data/__init__.py
relex/data/relex_corpus.py
relex/data/relex_dataset.py
relex/learners/__init__.py
relex/learners/entities_tagger_learner.py
relex/learners/pair_classifier_learner.py
relex/models/__init__.py
relex/models/entities_tagger.py
relex/models/pair_classifier.py
relex/predictors/__init__.py
relex/predictors/greedy_predictor.py
relex/utilities/__init__.py
relex/utilities/utils.py