Metadata-Version: 2.1
Name: relex
Version: 0.1.1
Summary: An easy to use PyTorch-based library for state-of-the-art semantic relations extraction.
Home-page: https://github.com/ylaxor/relex
Download-URL: https://github.com/ylaxor/relex/archive/refs/tags/v0.1.1.tar.gz
Author: Ali NCIBI
License: MIT
Keywords: PyTorch,Semantic Relation Extraction,Pipeline,Text analysis,NLP,NLU,Deep learning,AI
Platform: UNKNOWN
Requires-Python: >=3.7.13
